infra_sdk/__init__.py
infra_sdk/cli.py
infra_sdk/config.py
infra_sdk/state.py
infra_sdk-0.1.0.dist-info/METADATA
infra_sdk-0.1.0.dist-info/WHEEL
infra_sdk-0.1.0.dist-info/entry_points.txt
infra_sdk-0.1.0.dist-info/licenses/LICENSE
infra_sdk-0.1.0.dist-info/RECORD
