Metadata-Version: 2.3
Name: infra-sdk
Version: 0.1.0
Summary: Infrastructure management CLI using OpenTofu
Project-URL: Homepage, https://github.com/yourusername/infra-sdk
Project-URL: Repository, https://github.com/yourusername/infra-sdk.git
Project-URL: Issues, https://github.com/yourusername/infra-sdk/issues
Author-email: Your Name <your.email@example.com>
License: MIT
Keywords: cli,infrastructure,opentofu,terraform
Classifier: Development Status :: 3 - Alpha
Classifier: Environment :: Console
Classifier: Intended Audience :: Developers
Classifier: License :: OSI Approved :: MIT License
Classifier: Programming Language :: Python :: 3
Classifier: Programming Language :: Python :: 3.8
Classifier: Programming Language :: Python :: 3.9
Classifier: Programming Language :: Python :: 3.10
Classifier: Programming Language :: Python :: 3.11
Classifier: Topic :: Software Development :: Build Tools
Requires-Python: >=3.8
Requires-Dist: beaupy>=3.5.4
Requires-Dist: pyyaml>=6.0.0
Requires-Dist: rich>=10.0.0
Requires-Dist: sqlalchemy>=2.0.0
Requires-Dist: typer>=0.9.0
